Day10_modulo_n_counter/modulo_n_counter.v
`timescale 1ns/1ps

module modulo_n_counter #(
    parameter WIDTH = 8
)(
    input  wire             clk,
    input  wire             rst,
    input  wire             en,
    input  wire [WIDTH-1:0] mod_val,

    output reg  [WIDTH-1:0] count,
    output reg              tc
);

    always @(posedge clk) begin
        if (rst) begin
            count <= 0;
            tc    <= 0;
        end
        else begin
            // Default: terminal count pulse is low
            tc <= 0;

            // Invalid modulo value
            if (mod_val == 0) begin
                count <= 0;
            end

            // Count only when enabled
            else if (en) begin

                // Terminal count reached
                if (count == mod_val - 1) begin
                    count <= 0;
                    tc    <= 1;
                end
                else begin
                    count <= count + 1'b1;
                end
            end
        end
    end

endmodule

Day10_modulo_n_counter/tb.v
`timescale 1ns/1ps

module tb;

    parameter WIDTH = 8;

    reg clk;
    reg rst;
    reg en;
    reg [WIDTH-1:0] mod_val;

    wire [WIDTH-1:0] count;
    wire tc;

    // DUT
    modulo_n_counter #(
        .WIDTH(WIDTH)
    ) dut (
        .clk(clk),
        .rst(rst),
        .en(en),
        .mod_val(mod_val),
        .count(count),
        .tc(tc)
    );

    // Clock: 10 ns period
    always #5 clk = ~clk;

    // VCD dump
    initial begin
        $dumpfile("modulo_n_counter.vcd");
        $dumpvars(0, tb);
    end

    // Monitor signals
    initial begin
        $monitor("Time=%0t | rst=%b en=%b mod_val=%0d count=%0d tc=%b",
                 $time, rst, en, mod_val, count, tc);
    end

    initial begin

        // Initial values
        clk     = 0;
        rst     = 1;
        en      = 0;
        mod_val = 5;

        // Reset
        #12;
        rst = 0;

        // -----------------------------------
        // Test 1: Normal modulo-5 counting
        // -----------------------------------
        $display("\n--- TEST 1: MODULO 5 ---");

        en = 1;

        #60;

        // -----------------------------------
        // Test 2: Disable counting
        // -----------------------------------
        $display("\n--- TEST 2: ENABLE = 0 ---");

        en = 0;

        #30;

        // -----------------------------------
        // Test 3: Enable again
        // -----------------------------------
        $display("\n--- TEST 3: ENABLE = 1 ---");

        en = 1;

        #30;

        // -----------------------------------
        // Test 4: MODULO 1
        // -----------------------------------
        $display("\n--- TEST 4: MODULO 1 ---");

        mod_val = 1;

        #40;

        // -----------------------------------
        // Test 5: MODULO 0
        // -----------------------------------
        $display("\n--- TEST 5: MODULO 0 ---");

        mod_val = 0;

        #30;

        // -----------------------------------
        // Test 6: Change back to MODULO 4
        // -----------------------------------
        $display("\n--- TEST 6: MODULO 4 ---");

        mod_val = 4;

        #50;

        // Finish
        $display("\n--- SIMULATION COMPLETE ---");

        $finish;
    end

endmodule

Day10_modulo_n_counter/modulo_n_counter.vcd
$date
	Sat Aug 22 22:09:50 2026
$end
$version
	Icarus Verilog
$end
$timescale
	1ps
$end
$scope module tb $end
$var wire 1 ! tc $end
$var wire 8 " count [7:0] $end
$var parameter 32 # WIDTH $end
$var reg 1 $ clk $end
$var reg 1 % en $end
$var reg 8 & mod_val [7:0] $end
$var reg 1 ' rst $end
$scope module dut $end
$var wire 1 $ clk $end
$var wire 1 % en $end
$var wire 8 ( mod_val [7:0] $end
$var wire 1 ' rst $end
$var parameter 32 ) WIDTH $end
$var reg 8 * count [7:0] $end
$var reg 1 ! tc $end
$upscope $end
$upscope $end
$enddefinitions $end
$comment Show the parameter values. $end
$dumpall
b1000 )
b1000 #
$end
#0
$dumpvars
bx *
b101 (
1'
b101 &
0%
0$
bx "
x!
$end
#5000
0!
b0 "
b0 *
1$
#10000
0$
#12000
1%
0'
#15000
b1 "
b1 *
1$
#20000
0$
#25000
b10 "
b10 *
1$
#30000
0$
#35000
b11 "
b11 *
1$
#40000
0$
#45000
b100 "
b100 *
1$
#50000
0$
#55000
1!
b0 "
b0 *
1$
#60000
0$
#65000
b1 "
b1 *
0!
1$
#70000
0$
#72000
0%
#75000
1$
#80000
0$
#85000
1$
#90000
0$
#95000
1$
#100000
0$
#102000
1%
#105000
b10 "
b10 *
1$
#110000
0$
#115000
b11 "
b11 *
1$
#120000
0$
#125000
b100 "
b100 *
1$
#130000
0$
#132000
b1 &
b1 (
#135000
b101 "
b101 *
1$
#140000
0$
#145000
b110 "
b110 *
1$
#150000
0$
#155000
b111 "
b111 *
1$
#160000
0$
#165000
b1000 "
b1000 *
1$
#170000
0$
#172000
b0 &
b0 (
#175000
b0 "
b0 *
1$
#180000
0$
#185000
1$
#190000
0$
#195000
1$
#200000
0$
#202000
b100 &
b100 (
#205000
b1 "
b1 *
1$
#210000
0$
#215000
b10 "
b10 *
1$
#220000
0$
#225000
b11 "
b11 *
1$
#230000
0$
#235000
1!
b0 "
b0 *
1$
#240000
0$
#245000
b1 "
b1 *
0!
1$
